airflow_kdb_provider/__init__.py
airflow_kdb_provider/operators/__init__.py
airflow_kdb_provider/operators/kdb_operator.py
airflow_kdb_provider-0.1.3.dist-info/LICENSE
airflow_kdb_provider-0.1.3.dist-info/METADATA
airflow_kdb_provider-0.1.3.dist-info/WHEEL
airflow_kdb_provider-0.1.3.dist-info/top_level.txt
airflow_kdb_provider-0.1.3.dist-info/RECORD
