Metadata-Version: 2.1
Name: airflow-kdb-provider
Version: 0.1.3
Summary: Apache Airflow provider for KDBAirflowOperator
Home-page: UNKNOWN
Author: Kabir Jaiswal
Author-email: kabirjaiswal30@gmail.com
License: Apache License 2.0
Platform: UNKNOWN
Classifier: Development Status :: 3 - Alpha
Classifier: Intended Audience :: Developers
Classifier: License :: OSI Approved :: Apache Software License
Classifier: Programming Language :: Python :: 3
Requires-Dist: apache-airflow (>=2.0.0)
